{"type": "FeatureCollection", "features": [{"type": "Feature", "geometry": {"type": "Polygon", "coordinates": [[[-94.4289, 49.3845], [-94.4289, 48.366], [-95.3426, 48.366], [-95.3426, 49.3845], [-94.4289, 49.3845]]]}, "properties": {"County": "Lake Of The Woods County", "State": "Minnesota"}}, {"type": "Feature", "geometry": {"type": "Polygon", "coordinates": [[[-96.3866, 49.0005], [-96.3866, 48.5432], [-97.2392, 48.5432], [-97.2392, 49.0005], [-96.3866, 49.0005]]]}, "properties": {"County": "Kittson County", "State": "Minnesota"}}, {"type": "Feature", "geometry": {"type": "Polygon", "coordinates": [[[-95.0899, 49.0001], [-95.0899, 48.5386], [-96.4055, 48.5386], [-96.4055, 49.0001], [-95.0899, 49.0001]]]}, "properties": {"County": "Roseau County", "State": "Minnesota"}}, {"type": "Feature", "geometry": {"type": "Polygon", "coordinates": [[[-93.0808, 48.7119], [-93.0808, 47.8458], [-94.4304, 47.8458], [-94.4304, 48.7119], [-93.0808, 48.7119]]]}, "properties": {"County": "Koochiching County", "State": "Minnesota"}}, {"type": "Feature", "geometry": {"type": "Polygon", "coordinates": [[[-95.5932, 48.5451], [-95.5932, 48.1716], [-97.1634, 48.1716], [-97.1634, 48.5451], [-95.5932, 48.5451]]]}, "properties": {"County": "Marshall County", "State": "Minnesota"}}, {"type": "Feature", "geometry": {"type": "Polygon", "coordinates": [[[-91.7879, 48.6315], [-91.7879, 46.6492], [-93.098, 46.6492], [-93.098, 48.6315], [-91.7879, 48.6315]]]}, "properties": {"County": "St. Louis County", "State": "Minnesota"}}, {"type": "Feature", "geometry": {"type": "Polygon", "coordinates": [[[-94.4137, 48.5403], [-94.4137, 47.4095], [-95.6027, 47.4095], [-95.6027, 48.5403], [-94.4137, 48.5403]]]}, "properties": {"County": "Beltrami County", "State": "Minnesota"}}, {"type": "Feature", "geometry": {"type": "Polygon", "coordinates": [[[-95.5514, 48.1741], [-95.5514, 47.4986], [-97.1475, 47.4986], [-97.1475, 48.1741], [-95.5514, 48.1741]]]}, "properties": {"County": "Polk County", "State": "Minnesota"}}, {"type": "Feature", "geometry": {"type": "Polygon", "coordinates": [[[-95.5824, 48.1751], [-95.5824, 47.9338], [-96.501, 47.9338], [-96.501, 48.1751], [-95.5824, 48.1751]]]}, "properties": {"County": "Pennington County", "State": "Minnesota"}}, {"type": "Feature", "geometry": {"type": "Polygon", "coordinates": [[[-89.4918, 48.246], [-89.4918, 47.465], [-91.032, 47.465], [-91.032, 48.246], [-89.4918, 48.246]]]}, "properties": {"County": "Cook County", "State": "Minnesota"}}, {"type": "Feature", "geometry": {"type": "Polygon", "coordinates": [[[-91.0208, 48.206], [-91.0208, 46.9397], [-91.8002, 46.9397], [-91.8002, 48.206], [-91.0208, 48.206]]]}, "properties": {"County": "Lake County", "State": "Minnesota"}}, {"type": "Feature", "geometry": {"type": "Polygon", "coordinates": [[[-95.1691, 48.0208], [-95.1691, 47.1512], [-95.5828, 47.1512], [-95.5828, 48.0208], [-95.1691, 48.0208]]]}, "properties": {"County": "Clearwater County", "State": "Minnesota"}}, {"type": "Feature", "geometry": {"type": "Polygon", "coordinates": [[[-95.709, 47.9649], [-95.709, 47.7597], [-96.4828, 47.7597], [-96.4828, 47.9649], [-95.709, 47.9649]]]}, "properties": {"County": "Red Lake County", "State": "Minnesota"}}, {"type": "Feature", "geometry": {"type": "Polygon", "coordinates": [[[-93.0557, 47.8991], [-93.0557, 47.0253], [-94.4192, 47.0253], [-94.4192, 47.8991], [-93.0557, 47.8991]]]}, "properties": {"County": "Itasca County", "State": "Minnesota"}}, {"type": "Feature", "geometry": {"type": "Polygon", "coordinates": [[[-96.0667, 47.4999], [-96.0667, 47.1506], [-96.8718, 47.1506], [-96.8718, 47.4999], [-96.0667, 47.4999]]]}, "properties": {"County": "Norman County", "State": "Minnesota"}}, {"type": "Feature", "geometry": {"type": "Polygon", "coordinates": [[[-95.5503, 47.5001], [-95.5503, 47.1502], [-96.0676, 47.1502], [-96.0676, 47.5001], [-95.5503, 47.5001]]]}, "properties": {"County": "Mahnomen County", "State": "Minnesota"}}, {"type": "Feature", "geometry": {"type": "Polygon", "coordinates": [[[-93.7727, 47.4807], [-93.7727, 46.2766], [-94.7871, 46.2766], [-94.7871, 47.4807], [-93.7727, 47.4807]]]}, "properties": {"County": "Cass County", "State": "Minnesota"}}, {"type": "Feature", "geometry": {"type": "Polygon", "coordinates": [[[-94.6584, 47.4127], [-94.6584, 46.8037], [-95.1831, 46.8037], [-95.1831, 47.4127], [-94.6584, 47.4127]]]}, "properties": {"County": "Hubbard County", "State": "Minnesota"}}, {"type": "Feature", "geometry": {"type": "Polygon", "coordinates": [[[-96.1725, 47.1515], [-96.1725, 46.6286], [-96.8402, 46.6286], [-96.8402, 47.1515], [-96.1725, 47.1515]]]}, "properties": {"County": "Clay County", "State": "Minnesota"}}, {"type": "Feature", "geometry": {"type": "Polygon", "coordinates": [[[-95.1622, 47.1526], [-95.1622, 46.7155], [-96.1946, 46.7155], [-96.1946, 47.1526], [-95.1622, 47.1526]]]}, "properties": {"County": "Becker County", "State": "Minnesota"}}, {"type": "Feature", "geometry": {"type": "Polygon", "coordinates": [[[-93.0534, 47.0303], [-93.0534, 46.1541], [-93.812, 46.1541], [-93.812, 47.0303], [-93.0534, 47.0303]]]}, "properties": {"County": "Aitkin County", "State": "Minnesota"}}, {"type": "Feature", "geometry": {"type": "Polygon", "coordinates": [[[-94.728, 46.8055], [-94.728, 46.3684], [-95.1641, 46.3684], [-95.1641, 46.8055], [-94.728, 46.8055]]]}, "properties": {"County": "Wadena County", "State": "Minnesota"}}, {"type": "Feature", "geometry": {"type": "Polygon", "coordinates": [[[-93.776, 46.8054], [-93.776, 46.1559], [-94.3952, 46.1559], [-94.3952, 46.8054], [-93.776, 46.8054]]]}, "properties": {"County": "Crow Wing County", "State": "Minnesota"}}, {"type": "Feature", "geometry": {"type": "Polygon", "coordinates": [[[-92.2916, 46.7691], [-92.2916, 46.4173], [-93.0645, 46.4173], [-93.0645, 46.7691], [-92.2916, 46.7691]]]}, "properties": {"County": "Carlton County", "State": "Minnesota"}}, {"type": "Feature", "geometry": {"type": "Polygon", "coordinates": [[[-95.1457, 46.7182], [-95.1457, 46.1068], [-96.2813, 46.1068], [-96.2813, 46.7182], [-95.1457, 46.7182]]]}, "properties": {"County": "Otter Tail County", "State": "Minnesota"}}, {"type": "Feature", "geometry": {"type": "Polygon", "coordinates": [[[-96.2649, 46.6308], [-96.2649, 46.0216], [-96.7914, 46.0216], [-96.7914, 46.6308], [-96.2649, 46.6308]]]}, "properties": {"County": "Wilkin County", "State": "Minnesota"}}, {"type": "Feature", "geometry": {"type": "Polygon", "coordinates": [[[-92.2928, 46.4193], [-92.2928, 45.7301], [-93.1428, 45.7301], [-93.1428, 46.4193], [-92.2928, 46.4193]]]}, "properties": {"County": "Pine County", "State": "Minnesota"}}, {"type": "Feature", "geometry": {"type": "Polygon", "coordinates": [[[-94.6435, 46.3689], [-94.6435, 45.7734], [-95.1556, 45.7734], [-95.1556, 46.3689], [-94.6435, 46.3689]]]}, "properties": {"County": "Todd County", "State": "Minnesota"}}, {"type": "Feature", "geometry": {"type": "Polygon", "coordinates": [[[-93.7635, 46.3486], [-93.7635, 45.7739], [-94.6533, 45.7739], [-94.6533, 46.3486], [-93.7635, 46.3486]]]}, "properties": {"County": "Morrison County", "State": "Minnesota"}}, {"type": "Feature", "geometry": {"type": "Polygon", "coordinates": [[[-93.4296, 46.2472], [-93.4296, 45.5587], [-93.8108, 45.5587], [-93.8108, 46.2472], [-93.4296, 46.2472]]]}, "properties": {"County": "Mille Lacs County", "State": "Minnesota"}}, {"type": "Feature", "geometry": {"type": "Polygon", "coordinates": [[[-93.054, 46.1594], [-93.054, 45.7305], [-93.519, 45.7305], [-93.519, 46.1594], [-93.054, 46.1594]]]}, "properties": {"County": "Kanabec County", "State": "Minnesota"}}, {"type": "Feature", "geometry": {"type": "Polygon", "coordinates": [[[-95.7584, 46.1087], [-95.7584, 45.7592], [-96.2665, 45.7592], [-96.2665, 46.1087], [-95.7584, 46.1087]]]}, "properties": {"County": "Grant County", "State": "Minnesota"}}, {"type": "Feature", "geometry": {"type": "Polygon", "coordinates": [[[-95.1388, 46.1083], [-95.1388, 45.7588], [-95.7698, 45.7588], [-95.7698, 46.1083], [-95.1388, 46.1083]]]}, "properties": {"County": "Douglas County", "State": "Minnesota"}}, {"type": "Feature", "geometry": {"type": "Polygon", "coordinates": [[[-96.253, 46.0221], [-96.253, 45.5854], [-96.8578, 45.5854], [-96.8578, 46.0221], [-96.253, 46.0221]]]}, "properties": {"County": "Traverse County", "State": "Minnesota"}}, {"type": "Feature", "geometry": {"type": "Polygon", "coordinates": [[[-93.7593, 45.8243], [-93.7593, 45.559], [-94.3531, 45.559], [-94.3531, 45.8243], [-93.7593, 45.8243]]]}, "properties": {"County": "Benton County", "State": "Minnesota"}}, {"type": "Feature", "geometry": {"type": "Polygon", "coordinates": [[[-95.7475, 45.7599], [-95.7475, 45.4119], [-96.2541, 45.4119], [-96.2541, 45.7599], [-95.7475, 45.7599]]]}, "properties": {"County": "Stevens County", "State": "Minnesota"}}, {"type": "Feature", "geometry": {"type": "Polygon", "coordinates": [[[-94.0465, 45.7754], [-94.0465, 45.2824], [-95.1398, 45.2824], [-95.1398, 45.7754], [-94.0465, 45.7754]]]}, "properties": {"County": "Stearns County", "State": "Minnesota"}}, {"type": "Feature", "geometry": {"type": "Polygon", "coordinates": [[[-95.1314, 45.7599], [-95.1314, 45.4119], [-95.7586, 45.4119], [-95.7586, 45.7599], [-95.1314, 45.7599]]]}, "properties": {"County": "Pope County", "State": "Minnesota"}}, {"type": "Feature", "geometry": {"type": "Polygon", "coordinates": [[[-93.0196, 45.7343], [-93.0196, 45.4117], [-93.5136, 45.4117], [-93.5136, 45.7343], [-93.0196, 45.7343]]]}, "properties": {"County": "Isanti County", "State": "Minnesota"}}, {"type": "Feature", "geometry": {"type": "Polygon", "coordinates": [[[-92.6465, 45.7311], [-92.6465, 45.2962], [-93.1423, 45.2962], [-93.1423, 45.7311], [-92.6465, 45.7311]]]}, "properties": {"County": "Chisago County", "State": "Minnesota"}}, {"type": "Feature", "geometry": {"type": "Polygon", "coordinates": [[[-96.1036, 45.5861], [-96.1036, 45.1767], [-96.8355, 45.1767], [-96.8355, 45.5861], [-96.1036, 45.5861]]]}, "properties": {"County": "Big Stone County", "State": "Minnesota"}}, {"type": "Feature", "geometry": {"type": "Polygon", "coordinates": [[[-93.5098, 45.5602], [-93.5098, 45.246], [-94.1504, 45.246], [-94.1504, 45.5602], [-93.5098, 45.5602]]]}, "properties": {"County": "Sherburne County", "State": "Minnesota"}}, {"type": "Feature", "geometry": {"type": "Polygon", "coordinates": [[[-95.2465, 45.4127], [-95.2465, 45.1512], [-96.1185, 45.1512], [-96.1185, 45.4127], [-95.2465, 45.4127]]]}, "properties": {"County": "Swift County", "State": "Minnesota"}}, {"type": "Feature", "geometry": {"type": "Polygon", "coordinates": [[[-94.7568, 45.413], [-94.7568, 44.8913], [-95.2553, 44.8913], [-95.2553, 45.413], [-94.7568, 45.413]]]}, "properties": {"County": "Kandiyohi County", "State": "Minnesota"}}, {"type": "Feature", "geometry": {"type": "Polygon", "coordinates": [[[-93.5147, 45.4238], [-93.5147, 44.9777], [-94.2615, 44.9777], [-94.2615, 45.4238], [-93.5147, 45.4238]]]}, "properties": {"County": "Wright County", "State": "Minnesota"}}, {"type": "Feature", "geometry": {"type": "Polygon", "coordinates": [[[-93.0185, 45.4148], [-93.0185, 45.0355], [-93.5125, 45.0355], [-93.5125, 45.4148], [-93.0185, 45.4148]]]}, "properties": {"County": "Anoka County", "State": "Minnesota"}}, {"type": "Feature", "geometry": {"type": "Polygon", "coordinates": [[[-94.2555, 45.3266], [-94.2555, 44.8919], [-94.7635, 44.8919], [-94.7635, 45.3266], [-94.2555, 45.3266]]]}, "properties": {"County": "Meeker County", "State": "Minnesota"}}, {"type": "Feature", "geometry": {"type": "Polygon", "coordinates": [[[-95.7366, 45.2694], [-95.7366, 44.8048], [-96.4529, 44.8048], [-96.4529, 45.2694], [-95.7366, 45.2694]]]}, "properties": {"County": "Lac Qui Parle County", "State": "Minnesota"}}, {"type": "Feature", "geometry": {"type": "Polygon", "coordinates": [[[-92.7409, 45.2969], [-92.7409, 44.7457], [-93.0226, 44.7457], [-93.0226, 45.2969], [-92.7409, 45.2969]]]}, "properties": {"County": "Washington County", "State": "Minnesota"}}, {"type": "Feature", "geometry": {"type": "Polygon", "coordinates": [[[-93.1767, 45.247], [-93.1767, 44.7853], [-93.7678, 44.7853], [-93.7678, 45.247], [-93.1767, 45.247]]]}, "properties": {"County": "Hennepin County", "State": "Minnesota"}}, {"type": "Feature", "geometry": {"type": "Polygon", "coordinates": [[[-95.2465, 45.1528], [-95.2465, 44.7511], [-96.037, 44.7511], [-96.037, 45.1528], [-95.2465, 45.1528]]]}, "properties": {"County": "Chippewa County", "State": "Minnesota"}}, {"type": "Feature", "geometry": {"type": "Polygon", "coordinates": [[[-92.9841, 45.1245], [-92.9841, 44.8873], [-93.2279, 44.8873], [-93.2279, 45.1245], [-92.9841, 45.1245]]]}, "properties": {"County": "Ramsey County", "State": "Minnesota"}}, {"type": "Feature", "geometry": {"type": "Polygon", "coordinates": [[[-94.0099, 44.9798], [-94.0099, 44.6299], [-94.5024, 44.6299], [-94.5024, 44.9798], [-94.0099, 44.9798]]]}, "properties": {"County": "Mcleod County", "State": "Minnesota"}}, {"type": "Feature", "geometry": {"type": "Polygon", "coordinates": [[[-93.5203, 44.9786], [-93.5203, 44.6346], [-94.0125, 44.6346], [-94.0125, 44.9786], [-93.5203, 44.9786]]]}, "properties": {"County": "Carver County", "State": "Minnesota"}}, {"type": "Feature", "geometry": {"type": "Polygon", "coordinates": [[[-95.3602, 44.9359], [-95.3602, 44.5417], [-96.4519, 44.5417], [-96.4519, 44.9359], [-95.3602, 44.9359]]]}, "properties": {"County": "Yellow Medicine County", "State": "Minnesota"}}, {"type": "Feature", "geometry": {"type": "Polygon", "coordinates": [[[-92.7322, 44.9233], [-92.7322, 44.4712], [-93.3296, 44.4712], [-93.3296, 44.9233], [-92.7322, 44.9233]]]}, "properties": {"County": "Dakota County", "State": "Minnesota"}}, {"type": "Feature", "geometry": {"type": "Polygon", "coordinates": [[[-94.4977, 44.8923], [-94.4977, 44.456], [-95.4834, 44.456], [-95.4834, 44.8923], [-94.4977, 44.8923]]]}, "properties": {"County": "Renville County", "State": "Minnesota"}}, {"type": "Feature", "geometry": {"type": "Polygon", "coordinates": [[[-93.2779, 44.8125], [-93.2779, 44.5431], [-93.9116, 44.5431], [-93.9116, 44.8125], [-93.2779, 44.8125]]]}, "properties": {"County": "Scott County", "State": "Minnesota"}}, {"type": "Feature", "geometry": {"type": "Polygon", "coordinates": [[[-93.7638, 44.7179], [-93.7638, 44.4559], [-94.6295, 44.4559], [-94.6295, 44.7179], [-93.7638, 44.7179]]]}, "properties": {"County": "Sibley County", "State": "Minnesota"}}, {"type": "Feature", "geometry": {"type": "Polygon", "coordinates": [[[-94.8655, 44.6986], [-94.8655, 44.1951], [-95.5947, 44.1951], [-95.5947, 44.6986], [-94.8655, 44.6986]]]}, "properties": {"County": "Redwood County", "State": "Minnesota"}}, {"type": "Feature", "geometry": {"type": "Polygon", "coordinates": [[[-92.242, 44.7137], [-92.242, 44.1949], [-93.0412, 44.1949], [-93.0412, 44.7137], [-92.242, 44.7137]]]}, "properties": {"County": "Goodhue County", "State": "Minnesota"}}, {"type": "Feature", "geometry": {"type": "Polygon", "coordinates": [[[-96.0785, 44.6313], [-96.0785, 44.1967], [-96.4528, 44.1967], [-96.4528, 44.6313], [-96.0785, 44.6313]]]}, "properties": {"County": "Lincoln County", "State": "Minnesota"}}, {"type": "Feature", "geometry": {"type": "Polygon", "coordinates": [[[-95.5933, 44.6308], [-95.5933, 44.1951], [-96.0935, 44.1951], [-96.0935, 44.6308], [-95.5933, 44.6308]]]}, "properties": {"County": "Lyon County", "State": "Minnesota"}}, {"type": "Feature", "geometry": {"type": "Polygon", "coordinates": [[[-93.5242, 44.544], [-93.5242, 44.1959], [-94.0253, 44.1959], [-94.0253, 44.544], [-93.5242, 44.544]]]}, "properties": {"County": "Le Sueur County", "State": "Minnesota"}}, {"type": "Feature", "geometry": {"type": "Polygon", "coordinates": [[[-93.0393, 44.5441], [-93.0393, 44.1962], [-93.5256, 44.1962], [-93.5256, 44.5441], [-93.0393, 44.5441]]]}, "properties": {"County": "Rice County", "State": "Minnesota"}}, {"type": "Feature", "geometry": {"type": "Polygon", "coordinates": [[[-94.3688, 44.498], [-94.3688, 44.1078], [-95.1086, 44.1078], [-95.1086, 44.498], [-94.3688, 44.498]]]}, "properties": {"County": "Brown County", "State": "Minnesota"}}, {"type": "Feature", "geometry": {"type": "Polygon", "coordinates": [[[-93.9275, 44.4568], [-93.9275, 44.1539], [-94.7869, 44.1539], [-94.7869, 44.4568], [-93.9275, 44.4568]]]}, "properties": {"County": "Nicollet County", "State": "Minnesota"}}, {"type": "Feature", "geometry": {"type": "Polygon", "coordinates": [[[-91.8586, 44.4554], [-91.8586, 44.1068], [-92.5509, 44.1068], [-92.5509, 44.4554], [-91.8586, 44.4554]]]}, "properties": {"County": "Wabasha County", "State": "Minnesota"}}, {"type": "Feature", "geometry": {"type": "Polygon", "coordinates": [[[-93.7676, 44.2644], [-93.7676, 43.8479], [-94.3718, 43.8479], [-94.3718, 44.2644], [-93.7676, 44.2644]]]}, "properties": {"County": "Blue Earth County", "State": "Minnesota"}}, {"type": "Feature", "geometry": {"type": "Polygon", "coordinates": [[[-96.0637, 44.1975], [-96.0637, 43.8486], [-96.4535, 43.8486], [-96.4535, 44.1975], [-96.0637, 44.1975]]]}, "properties": {"County": "Pipestone County", "State": "Minnesota"}}, {"type": "Feature", "geometry": {"type": "Polygon", "coordinates": [[[-95.4621, 44.1966], [-95.4621, 43.8479], [-96.0646, 43.8479], [-96.0646, 44.1966], [-95.4621, 44.1966]]]}, "properties": {"County": "Murray County", "State": "Minnesota"}}, {"type": "Feature", "geometry": {"type": "Polygon", "coordinates": [[[-94.859, 44.196], [-94.859, 43.8477], [-95.4625, 43.8477], [-95.4625, 44.196], [-94.859, 44.196]]]}, "properties": {"County": "Cottonwood County", "State": "Minnesota"}}, {"type": "Feature", "geometry": {"type": "Polygon", "coordinates": [[[-91.2842, 44.1933], [-91.2842, 43.8468], [-92.0794, 43.8468], [-92.0794, 44.1933], [-91.2842, 44.1933]]]}, "properties": {"County": "Winona County", "State": "Minnesota"}}, {"type": "Feature", "geometry": {"type": "Polygon", "coordinates": [[[-93.4062, 44.1964], [-93.4062, 43.8479], [-93.7684, 43.8479], [-93.7684, 44.1964], [-93.4062, 44.1964]]]}, "properties": {"County": "Waseca County", "State": "Minnesota"}}, {"type": "Feature", "geometry": {"type": "Polygon", "coordinates": [[[-93.0453, 44.1967], [-93.0453, 43.8481], [-93.4067, 43.8481], [-93.4067, 44.1967], [-93.0453, 44.1967]]]}, "properties": {"County": "Steele County", "State": "Minnesota"}}, {"type": "Feature", "geometry": {"type": "Polygon", "coordinates": [[[-92.6779, 44.197], [-92.6779, 43.8484], [-93.0459, 43.8484], [-93.0459, 44.197], [-92.6779, 44.197]]]}, "properties": {"County": "Dodge County", "State": "Minnesota"}}, {"type": "Feature", "geometry": {"type": "Polygon", "coordinates": [[[-92.0789, 44.1956], [-92.0789, 43.8338], [-92.6894, 43.8338], [-92.6894, 44.1956], [-92.0789, 44.1956]]]}, "properties": {"County": "Olmsted County", "State": "Minnesota"}}, {"type": "Feature", "geometry": {"type": "Polygon", "coordinates": [[[-94.3688, 44.109], [-94.3688, 43.848], [-94.8597, 43.848], [-94.8597, 44.109], [-94.3688, 44.109]]]}, "properties": {"County": "Watonwan County", "State": "Minnesota"}}, {"type": "Feature", "geometry": {"type": "Polygon", "coordinates": [[[-96.0523, 43.8496], [-96.0523, 43.5002], [-96.4535, 43.5002], [-96.4535, 43.8496], [-96.0523, 43.8496]]]}, "properties": {"County": "Rock County", "State": "Minnesota"}}, {"type": "Feature", "geometry": {"type": "Polygon", "coordinates": [[[-95.452, 43.8491], [-95.452, 43.4999], [-96.0536, 43.4999], [-96.0536, 43.8491], [-95.452, 43.8491]]]}, "properties": {"County": "Nobles County", "State": "Minnesota"}}, {"type": "Feature", "geometry": {"type": "Polygon", "coordinates": [[[-94.8544, 43.8481], [-94.8544, 43.5002], [-95.4544, 43.5002], [-95.4544, 43.8481], [-94.8544, 43.8481]]]}, "properties": {"County": "Jackson County", "State": "Minnesota"}}, {"type": "Feature", "geometry": {"type": "Polygon", "coordinates": [[[-94.2472, 43.8483], [-94.2472, 43.5001], [-94.8547, 43.5001], [-94.8547, 43.8483], [-94.2472, 43.8483]]]}, "properties": {"County": "Martin County", "State": "Minnesota"}}, {"type": "Feature", "geometry": {"type": "Polygon", "coordinates": [[[-91.2173, 43.8474], [-91.2173, 43.5005], [-91.7306, 43.5005], [-91.7306, 43.8474], [-91.2173, 43.8474]]]}, "properties": {"County": "Houston County", "State": "Minnesota"}}, {"type": "Feature", "geometry": {"type": "Polygon", "coordinates": [[[-93.648, 43.8482], [-93.648, 43.4996], [-94.248, 43.4996], [-94.248, 43.8482], [-93.648, 43.8482]]]}, "properties": {"County": "Faribault County", "State": "Minnesota"}}, {"type": "Feature", "geometry": {"type": "Polygon", "coordinates": [[[-91.7303, 43.8483], [-91.7303, 43.5005], [-92.4496, 43.5005], [-92.4496, 43.8483], [-91.7303, 43.8483]]]}, "properties": {"County": "Fillmore County", "State": "Minnesota"}}, {"type": "Feature", "geometry": {"type": "Polygon", "coordinates": [[[-93.0491, 43.8484], [-93.0491, 43.4994], [-93.6486, 43.4994], [-93.6486, 43.8484], [-93.0491, 43.8484]]]}, "properties": {"County": "Freeborn County", "State": "Minnesota"}}, {"type": "Feature", "geometry": {"type": "Polygon", "coordinates": [[[-92.4489, 43.8487], [-92.4489, 43.4997], [-93.0496, 43.4997], [-93.0496, 43.8487], [-92.4489, 43.8487]]]}, "properties": {"County": "Mower County", "State": "Minnesota"}}, {"type": "Feature", "geometry": {"type": "Polygon", "coordinates": [[[-89.5327, 47.996], [-89.5327, 47.9957], [-89.5334, 47.9957], [-89.5334, 47.996], [-89.5327, 47.996]]]}, "properties": {"County": "Cook County", "State": "Minnesota"}}, {"type": "Feature", "geometry": {"type": "Polygon", "coordinates": [[[-89.5357, 47.9957], [-89.5357, 47.995], [-89.537, 47.995], [-89.537, 47.9957], [-89.5357, 47.9957]]]}, "properties": {"County": "Cook County", "State": "Minnesota"}}, {"type": "Feature", "geometry": {"type": "Polygon", "coordinates": [[[-89.6541, 47.9564], [-89.6541, 47.9501], [-89.6659, 47.9501], [-89.6659, 47.9564], [-89.6541, 47.9564]]]}, "properties": {"County": "Cook County", "State": "Minnesota"}}, {"type": "Feature", "geometry": {"type": "Polygon", "coordinates": [[[-89.8269, 47.8815], [-89.8269, 47.8798], [-89.8291, 47.8798], [-89.8291, 47.8815], [-89.8269, 47.8815]]]}, "properties": {"County": "Cook County", "State": "Minnesota"}}, {"type": "Feature", "geometry": {"type": "Polygon", "coordinates": [[[-89.8379, 47.8782], [-89.8379, 47.8762], [-89.8401, 47.8762], [-89.8401, 47.8782], [-89.8379, 47.8782]]]}, "properties": {"County": "Cook County", "State": "Minnesota"}}, {"type": "Feature", "geometry": {"type": "Polygon", "coordinates": [[[-90.3289, 47.7458], [-90.3289, 47.745], [-90.3321, 47.745], [-90.3321, 47.7458], [-90.3289, 47.7458]]]}, "properties": {"County": "Cook County", "State": "Minnesota"}}, {"type": "Feature", "geometry": {"type": "Polygon", "coordinates": [[[-90.3342, 47.7455], [-90.3342, 47.7451], [-90.3352, 47.7451], [-90.3352, 47.7455], [-90.3342, 47.7455]]]}, "properties": {"County": "Cook County", "State": "Minnesota"}}, {"type": "Feature", "geometry": {"type": "Polygon", "coordinates": [[[-91.238, 47.2972], [-91.238, 47.2967], [-91.2396, 47.2967], [-91.2396, 47.2972], [-91.238, 47.2972]]]}, "properties": {"County": "Lake County", "State": "Minnesota"}}, {"type": "Feature", "geometry": {"type": "Polygon", "coordinates": [[[-91.2438, 47.2934], [-91.2438, 47.293], [-91.2442, 47.293], [-91.2442, 47.2934], [-91.2438, 47.2934]]]}, "properties": {"County": "Lake County", "State": "Minnesota"}}, {"type": "Feature", "geometry": {"type": "Polygon", "coordinates": [[[-91.2446, 47.2934], [-91.2446, 47.2921], [-91.2457, 47.2921], [-91.2457, 47.2934], [-91.2446, 47.2934]]]}, "properties": {"County": "Lake County", "State": "Minnesota"}}, {"type": "Feature", "geometry": {"type": "Polygon", "coordinates": [[[-91.5513, 47.0908], [-91.5513, 47.0875], [-91.5539, 47.0875], [-91.5539, 47.0908], [-91.5513, 47.0908]]]}, "properties": {"County": "Lake County", "State": "Minnesota"}}, {"type": "Feature", "geometry": {"type": "Polygon", "coordinates": [[[-91.7719, 46.9467], [-91.7719, 46.9458], [-91.7744, 46.9458], [-91.7744, 46.9467], [-91.7719, 46.9467]]]}, "properties": {"County": "Lake County", "State": "Minnesota"}}, {"type": "Feature", "geometry": {"type": "Polygon", "coordinates": [[[-89.5585, 47.9896], [-89.5585, 47.9886], [-89.5609, 47.9886], [-89.5609, 47.9896], [-89.5585, 47.9896]]]}, "properties": {"County": "Cook County", "State": "Minnesota"}}, {"type": "Feature", "geometry": {"type": "Polygon", "coordinates": [[[-89.5573, 47.9888], [-89.5573, 47.9883], [-89.5582, 47.9883], [-89.5582, 47.9888], [-89.5573, 47.9888]]]}, "properties": {"County": "Cook County", "State": "Minnesota"}}, {"type": "Feature", "geometry": {"type": "Polygon", "coordinates": [[[-89.5672, 47.9806], [-89.5672, 47.9678], [-89.5882, 47.9678], [-89.5882, 47.9806], [-89.5672, 47.9806]]]}, "properties": {"County": "Cook County", "State": "Minnesota"}}, {"type": "Feature", "geometry": {"type": "Polygon", "coordinates": [[[-89.5589, 47.9793], [-89.5589, 47.9777], [-89.5637, 47.9777], [-89.5637, 47.9793], [-89.5589, 47.9793]]]}, "properties": {"County": "Cook County", "State": "Minnesota"}}, {"type": "Feature", "geometry": {"type": "Polygon", "coordinates": [[[-89.6131, 47.9807], [-89.6131, 47.9795], [-89.6152, 47.9795], [-89.6152, 47.9807], [-89.6131, 47.9807]]]}, "properties": {"County": "Cook County", "State": "Minnesota"}}, {"type": "Feature", "geometry": {"type": "Polygon", "coordinates": [[[-89.587, 47.979], [-89.587, 47.9776], [-89.5929, 47.9776], [-89.5929, 47.979], [-89.587, 47.979]]]}, "properties": {"County": "Cook County", "State": "Minnesota"}}, {"type": "Feature", "geometry": {"type": "Polygon", "coordinates": [[[-89.5867, 47.9754], [-89.5867, 47.9738], [-89.5905, 47.9738], [-89.5905, 47.9754], [-89.5867, 47.9754]]]}, "properties": {"County": "Cook County", "State": "Minnesota"}}, {"type": "Feature", "geometry": {"type": "Polygon", "coordinates": [[[-89.552, 47.9733], [-89.552, 47.9692], [-89.5627, 47.9692], [-89.5627, 47.9733], [-89.552, 47.9733]]]}, "properties": {"County": "Cook County", "State": "Minnesota"}}, {"type": "Feature", "geometry": {"type": "Polygon", "coordinates": [[[-89.5876, 47.9736], [-89.5876, 47.9709], [-89.5957, 47.9709], [-89.5957, 47.9736], [-89.5876, 47.9736]]]}, "properties": {"County": "Cook County", "State": "Minnesota"}}, {"type": "Feature", "geometry": {"type": "Polygon", "coordinates": [[[-89.5625, 47.9719], [-89.5625, 47.9705], [-89.567, 47.9705], [-89.567, 47.9719], [-89.5625, 47.9719]]]}, "properties": {"County": "Cook County", "State": "Minnesota"}}, {"type": "Feature", "geometry": {"type": "Polygon", "coordinates": [[[-89.5786, 47.9692], [-89.5786, 47.9685], [-89.5799, 47.9685], [-89.5799, 47.9692], [-89.5786, 47.9692]]]}, "properties": {"County": "Cook County", "State": "Minnesota"}}, {"type": "Feature", "geometry": {"type": "Polygon", "coordinates": [[[-89.5665, 47.9679], [-89.5665, 47.9588], [-89.5871, 47.9588], [-89.5871, 47.9679], [-89.5665, 47.9679]]]}, "properties": {"County": "Cook County", "State": "Minnesota"}}, {"type": "Feature", "geometry": {"type": "Polygon", "coordinates": [[[-89.5865, 47.9682], [-89.5865, 47.9665], [-89.592, 47.9665], [-89.592, 47.9682], [-89.5865, 47.9682]]]}, "properties": {"County": "Cook County", "State": "Minnesota"}}, {"type": "Feature", "geometry": {"type": "Polygon", "coordinates": [[[-89.5872, 47.9621], [-89.5872, 47.9611], [-89.5894, 47.9611], [-89.5894, 47.9621], [-89.5872, 47.9621]]]}, "properties": {"County": "Cook County", "State": "Minnesota"}}, {"type": "Feature", "geometry": {"type": "Polygon", "coordinates": [[[-89.5813, 47.9566], [-89.5813, 47.9559], [-89.583, 47.9559], [-89.583, 47.9566], [-89.5813, 47.9566]]]}, "properties": {"County": "Cook County", "State": "Minnesota"}}, {"type": "Feature", "geometry": {"type": "Polygon", "coordinates": [[[-90.9097, 47.5259], [-90.9097, 47.5187], [-90.9214, 47.5187], [-90.9214, 47.5259], [-90.9097, 47.5259]]]}, "properties": {"County": "Cook County", "State": "Minnesota"}}, {"type": "Feature", "geometry": {"type": "Polygon", "coordinates": [[[-91.2666, 47.2703], [-91.2666, 47.2701], [-91.2671, 47.2701], [-91.2671, 47.2703], [-91.2666, 47.2703]]]}, "properties": {"County": "Lake County", "State": "Minnesota"}}, {"type": "Feature", "geometry": {"type": "Polygon", "coordinates": [[[-91.2819, 47.2659], [-91.2819, 47.2653], [-91.2828, 47.2653], [-91.2828, 47.2659], [-91.2819, 47.2659]]]}, "properties": {"County": "Lake County", "State": "Minnesota"}}]}